handd/__init__.py
handd/handd.py
handd-0.1.3.dist-info/METADATA
handd-0.1.3.dist-info/WHEEL
handd-0.1.3.dist-info/top_level.txt
handd-0.1.3.dist-info/RECORD
