Metadata-Version: 2.1
Name: handd
Version: 0.1.3
Summary: HAND-Drawn module for pycairo
Home-page: https://github.com/cobacdavid/handd
Author: David COBAC
Author-email: david.cobac@gmail.com
License: CC-BY-NC-SA
Keywords: hand-drawn,pycairo,realistic,drawing
Requires-Python: >3.6
Requires-Dist: pycairo
